[
    {
        "name": "Sapporo Regional Immigration Bureau",
        "lat": 43.062096,
        "lon": 141.354376
    },
    {
        "name": "Sendai Regional Immigration Bureau",
        "lat": 38.268215,
        "lon": 140.869356
    },
    {
        "name": "Tokyo Regional Immigration Bureau",
        "lat": 35.630184,
        "lon": 139.744451
    },
    {
        "name": "Yokohama Branch (Tokyo Immigration Office)",
        "lat": 35.327116,
        "lon": 139.652826
    },
    {
        "name": "Kawasaki Branch (Tokyo Immigration Office)",
        "lat": 35.603055,
        "lon": 139.507135
    },
    {
        "name": "Mito Branch (Tokyo Immigration Office)",
        "lat": 36.374641,
        "lon": 140.478825
    },
    {
        "name": "Utsunomiya Branch (Tokyo Immigration Office)",
        "lat": 36.555099,
        "lon": 139.882818
    },
    {
        "name": "Takasaki Branch (Tokyo Immigration Office)",
        "lat": 36.321404,
        "lon": 139.006202
    },
    {
        "name": "Saitama Branch (Tokyo Immigration Office)",
        "lat": 35.9126,
        "lon": 139.645482
    },
    {
        "name": "Chiba Branch (Tokyo Immigration Office)",
        "lat": 35.607377,
        "lon": 140.106863
    },
    {
        "name": "Matsudo Branch (Tokyo Immigration Office)",
        "lat": 35.785816,
        "lon": 139.903403
    },
    {
        "name": "Tachikawa Branch (Tokyo Immigration Office)",
        "lat": 35.69945,
        "lon": 139.406128
    },
    {
        "name": "Kofu Branch (Tokyo Immigration Office)",
        "lat": 35.663857,
        "lon": 138.568297
    },
    {
        "name": "Nagano Branch (Tokyo Immigration Office)",
        "lat": 36.651389,
        "lon": 138.181112
    },
    {
        "name": "Niigata Branch (Tokyo Immigration Office)",
        "lat": 37.95583,
        "lon": 139.11167
    },
    {
        "name": "Narita Airport Branch (Tokyo Immigration Office)",
        "lat": 35.776707,
        "lon": 140.318753
    },
    {
        "name": "Haneda Airport Branch (Tokyo Immigration Office)",
        "lat": 35.549393,
        "lon": 139.779839
    },
    {
        "name": "Nagoya Regional Immigration Bureau",
        "lat": 35.181446,
        "lon": 136.906398
    },
    {
        "name": "Toyohashi Port Branch (Nagoya Immigration Office)",
        "lat": 34.769362,
        "lon": 137.383362
    },
    {
        "name": "Shizuoka Branch (Nagoya Immigration Office)",
        "lat": 34.975556,
        "lon": 138.383056
    },
    {
        "name": "Hamamatsu Branch (Nagoya Immigration Office)",
        "lat": 34.710062,
        "lon": 137.726489
    },
    {
        "name": "Yokkaichi Port Branch (Nagoya Immigration Office)",
        "lat": 34.963122,
        "lon": 136.628732
    },
    {
        "name": "Gifu Branch (Nagoya Immigration Office)",
        "lat": 35.423298,
        "lon": 136.760197
    },
    {
        "name": "Kanazawa Branch (Nagoya Immigration Office)",
        "lat": 36.57806,
        "lon": 136.648647
    },
    {
        "name": "Fukui Branch (Nagoya Immigration Office)",
        "lat": 36.06268,
        "lon": 136.221635
    },
    {
        "name": "Osaka Regional Immigration Bureau",
        "lat": 34.693738,
        "lon": 135.502165
    },
    {
        "name": "Otsu Branch (Osaka Immigration Office)",
        "lat": 35.004532,
        "lon": 135.868514
    },
    {
        "name": "Kyoto Branch (Osaka Immigration Office)",
        "lat": 35.028611,
        "lon": 135.778807
    },
    {
        "name": "Maizuru Port Branch (Osaka Immigration Office)",
        "lat": 35.449185,
        "lon": 135.325028
    },
    {
        "name": "Nara Branch (Osaka Immigration Office)",
        "lat": 34.685121,
        "lon": 135.805
    },
    {
        "name": "Wakayama Branch (Osaka Immigration Office)",
        "lat": 34.225719,
        "lon": 135.167505
    },
    {
        "name": "Kansai Airport Branch (Osaka Immigration Office)",
        "lat": 34.431841,
        "lon": 135.219949
    },
    {
        "name": "Kobe Branch (Osaka Immigration Office)",
        "lat": 34.690083,
        "lon": 135.195511
    },
    {
        "name": "Himeji Port Branch (Osaka Immigration Office)",
        "lat": 34.815119,
        "lon": 134.650839
    },
    {
        "name": "Hiroshima Regional Immigration Bureau",
        "lat": 34.385203,
        "lon": 132.455292
    },
    {
        "name": "Sakaiminato Branch (Hiroshima Immigration Office)",
        "lat": 35.543003,
        "lon": 133.211334
    },
    {
        "name": "Matsue Branch (Hiroshima Immigration Office)",
        "lat": 35.472348,
        "lon": 133.05048
    },
    {
        "name": "Okayama Branch (Hiroshima Immigration Office)",
        "lat": 34.661784,
        "lon": 133.935264
    },
    {
        "name": "Fukuyama Branch (Hiroshima Immigration Office)",
        "lat": 34.480392,
        "lon": 133.362499
    },
    {
        "name": "Shimonoseki Port Branch (Hiroshima Immigration Office)",
        "lat": 33.957849,
        "lon": 130.94118
    },
    {
        "name": "Shunan Port Branch (Hiroshima Immigration Office)",
        "lat": 34.05862,
        "lon": 131.803115
    },
    {
        "name": "Takamatsu Regional Immigration Bureau",
        "lat": 34.342804,
        "lon": 134.046397
    },
    {
        "name": "Komatsushima Port Branch (Takamatsu Immigration Office)",
        "lat": 34.041681,
        "lon": 134.58168
    },
    {
        "name": "Matsuyama Branch (Takamatsu Immigration Office)",
        "lat": 33.839312,
        "lon": 132.765277
    },
    {
        "name": "Kochi Branch (Takamatsu Immigration Office)",
        "lat": 33.558211,
        "lon": 133.53109
    },
    {
        "name": "Fukuoka Regional Immigration Bureau",
        "lat": 33.590355,
        "lon": 130.401715
    },
    {
        "name": "Kitakyushu Branch (Fukuoka Immigration Office)",
        "lat": 33.883644,
        "lon": 130.875793
    },
    {
        "name": "Saga Branch (Fukuoka Immigration Office)",
        "lat": 33.249365,
        "lon": 130.299497
    },
    {
        "name": "Nagasaki Port Branch (Fukuoka Immigration Office)",
        "lat": 32.755349,
        "lon": 129.877538
    },
    {
        "name": "Tsushima Branch (Fukuoka Immigration Office)",
        "lat": 34.265376,
        "lon": 129.499338
    },
    {
        "name": "Kumamoto Branch (Fukuoka Immigration Office)",
        "lat": 32.803056,
        "lon": 130.707778
    },
    {
        "name": "Oita Branch (Fukuoka Immigration Office)",
        "lat": 33.238166,
        "lon": 131.609046
    },
    {
        "name": "Miyazaki Branch (Fukuoka Immigration Office)",
        "lat": 31.907572,
        "lon": 131.420225
    },
    {
        "name": "Kagoshima Port Branch (Fukuoka Immigration Office)",
        "lat": 31.596236,
        "lon": 130.557132
    },
    {
        "name": "Naha Branch (Fukuoka Immigration Office)",
        "lat": 26.212401,
        "lon": 127.680932
    },
    {
        "name": "Miyakojima Branch (Fukuoka Immigration Office)",
        "lat": 24.806927,
        "lon": 125.281373
    },
    {
        "name": "Ishigaki Port Branch (Fukuoka Immigration Office)",
        "lat": 24.343113,
        "lon": 124.158184
    },
    {
        "name": "Kadena Branch (Fukuoka Immigration Office)",
        "lat": 26.34037,
        "lon": 127.77679
    }
]
